[
{"page": 1, "link": 1, "repo": "TheAlgorithms/Python", "commit": "f1ce2d6"},
{"page": 1, "link": 10, "repo": "joeyajames/Python", "commit": "a097b55"},
{"page": 1, "link": 9, "repo": "docker-library/python", "commit": "81beb3f"},
{"page": 1, "link": 8, "repo": "jakevdp/PythonDataScienceHandbook", "commit": "8a34a4f"},
{"page": 1, "link": 7, "repo": "xxg1413/python", "commit": "565e367"},
{"page": 1, "link": 6, "repo": "kubernetes-client/python", "commit": "10671f9"},
{"page": 1, "link": 5, "repo": "Show-Me-the-Code/python", "commit": "1a7e3ed"},
{"page": 1, "link": 4, "repo": "TwoWater/Python", "commit": "7eb243f"},
{"page": 1, "link": 3, "repo": "injetlee/Python", "commit": "94faec4"},
{"page": 1, "link": 2, "repo": "geekcomputers/Python", "commit": "75d35e4"},
{"page": 2, "link": 1, "repo": "exercism/python", "commit": "b4bc89a"},
{"page": 2, "link": 10, "repo": "yidao620c/python3-cookbook", "commit": "913ea87"},
{"page": 2, "link": 9, "repo": "521xueweihan/python", "commit": "9434ffe"},
{"page": 2, "link": 8, "repo": "Pierian-Data/Complete-Python-3-Bootcamp", "commit": "046bae0"},
{"page": 2, "link": 7, "repo": "michaelliao/learn-python3", "commit": "9abe177"},
{"page": 2, "link": 6, "repo": "joe011/python", "commit": "fe00258"},
{"page": 2, "link": 5, "repo": "AtsushiSakai/PythonRobotics", "commit": "fa1585d"},
{"page": 2, "link": 4, "repo": "jackfrued/Python-100-Days", "commit": "3ef3721"},
{"page": 2, "link": 3, "repo": "vinta/awesome-python", "commit": "50a5dee"},
{"page": 2, "link": 2, "repo": "poise/python", "commit": "711e4d9"},
{"page": 3, "link": 9, "repo": "wistbean/learn_python3_spider", "commit": "fb7b5f5"},
{"page": 3, "link": 8, "repo": "Jack-Cherish/python-spider", "commit": "f256c15"},
{"page": 3, "link": 7, "repo": "taizilongxu/interview_python", "commit": "6dc27a1"},
{"page": 3, "link": 6, "repo": "gxcuizy/Python", "commit": "a634efe"},
{"page": 3, "link": 4, "repo": "realpython/python-guide", "commit": "adae3f0"},
{"page": 3, "link": 3, "repo": "faif/python-patterns", "commit": "588f39a"},
{"page": 3, "link": 2, "repo": "lining0806/PythonSpiderNotes", "commit": "78fee6c"},
{"page": 3, "link": 1, "repo": "zhanghe06/python", "commit": "a678ce3"},
{"page": 4, "link": 1, "repo": "dsacademybr/PythonFundamentos", "commit": "cc1611f"},
{"page": 4, "link": 10, "repo": "lijin-THU/notes-python", "commit": "f56440d"},
{"page": 4, "link": 9, "repo": "bigmlcom/python", "commit": "1fc8da1"},
{"page": 4, "link": 8, "repo": "xianhu/LearnPython", "commit": "b983bc4"},
{"page": 4, "link": 7, "repo": "zhiwehu/Python-programming-exercises", "commit": "22bb9b3"},
{"page": 4, "link": 6, "repo": "python/cpython", "commit": "261cfed"},
{"page": 3, "link": 10, "repo": "jobbole/awesome-python-cn", "commit": "4fdf5fa"},
{"page": 4, "link": 5, "repo": "boostorg/python", "commit": "1727b67"},
{"page": 4, "link": 4, "repo": "revolunet/PythonBooks", "commit": "9ef486c"},
{"page": 4, "link": 3, "repo": "DonJayamanne/pythonVSCode", "commit": "98e6aa5"},
{"page": 4, "link": 2, "repo": "gto76/python-cheatsheet", "commit": "6a6f900"},
{"page": 3, "link": 5, "repo": "michaelliao/awesome-python3-webapp", "commit": "1a7198e"},
{"page": 5, "link": 1, "repo": "nnja/python", "commit": "9888478"},
{"page": 5, "link": 8, "repo": "fchollet/deep-learning-with-python-notebooks", "commit": "8a30b90"},
{"page": 5, "link": 10, "repo": "17mon/python", "commit": "27d0980"},
{"page": 5, "link": 9, "repo": "smilejay/python", "commit": "e7e8106"},
{"page": 5, "link": 7, "repo": "GoogleCloudPlatform/python-docs-samples", "commit": "922f6e1"},
{"page": 5, "link": 6, "repo": "Tanu-N-Prabhu/Python", "commit": "aaddcf1"},
{"page": 5, "link": 5, "repo": "heyxiaohao/Python", "commit": "c7a15ff"},
{"page": 5, "link": 4, "repo": "aimacode/aima-python", "commit": "9ea91c1"},
{"page": 5, "link": 3, "repo": "gregmalcolm/python_koans", "commit": "75b7492"},
{"page": 5, "link": 2, "repo": "rasbt/python-machine-learning-book", "commit": "23853c5"},
{"page": 6, "link": 10, "repo": "adi0509/Python", "commit": "9626519"},
{"page": 6, "link": 9, "repo": "hussien89aa/PythonTutorial", "commit": "9c89b9b"},
{"page": 6, "link": 8, "repo": "mahmoud/awesome-python-applications", "commit": "6f0021b"},
{"page": 6, "link": 7, "repo": "Snailclimb/python", "commit": "9377415"},
{"page": 6, "link": 6, "repo": "Yonv1943/Python", "commit": "b4b9136"},
{"page": 6, "link": 5, "repo": "python-telegram-bot/python-telegram-bot", "commit": "15268ac"},
{"page": 6, "link": 4, "repo": "dabeaz-course/practical-python", "commit": "24cd6df"},
{"page": 6, "link": 3, "repo": "coodict/python3-in-one-pic", "commit": "4477fa5"},
{"page": 6, "link": 2, "repo": "google/python-fire", "commit": "457b156"},
{"page": 6, "link": 1, "repo": "Kr1s77/awesome-python-login-model", "commit": "9d6f845"},
{"page": 7, "link": 10, "repo": "yhangf/PythonCrawler", "commit": "d0a29c2"},
{"page": 7, "link": 9, "repo": "coucoueric/Python", "commit": "6fc3c19"},
{"page": 7, "link": 7, "repo": "Alfred1984/interesting-python", "commit": "b465986"},
{"page": 7, "link": 6, "repo": "dabeaz/python-cookbook", "commit": "6e46b78"},
{"page": 7, "link": 5, "repo": "susanli2016/Machine-Learning-with-Python", "commit": "0b6a920"},
{"page": 7, "link": 4, "repo": "JWarmenhoven/ISLR-python", "commit": "87ae8f9"},
{"page": 7, "link": 1, "repo": "REMitchell/python-scraping", "commit": "f04a5b7"},
{"page": 8, "link": 1, "repo": "dpkp/kafka-python", "commit": "f5a99fa"},
{"page": 8, "link": 10, "repo": "lancopku/pkuseg-python", "commit": "d581c95"},
{"page": 8, "link": 8, "repo": "jmportilla/Complete-Python-Bootcamp", "commit": "6b5531e"},
{"page": 8, "link": 6, "repo": "amueller/introduction_to_ml_with_python", "commit": "24dbadd"},
{"page": 8, "link": 5, "repo": "python-mode/python-mode", "commit": "51c66fa"},
{"page": 8, "link": 4, "repo": "jerry-git/learn-python3", "commit": "08ea8b7"},
{"page": 7, "link": 8, "repo": "wkunzhi/Python3-Spider", "commit": "abf08d6"},
{"page": 8, "link": 3, "repo": "matplotlib/matplotlib", "commit": "8589fed"},
{"page": 8, "link": 2, "repo": "Shekhar-rv/Python", "commit": "13abbe8"},
{"page": 7, "link": 3, "repo": "pubnub/python", "commit": "a252904"},
{"page": 7, "link": 2, "repo": "ThatEidolon/Python", "commit": "fcea97d"},
{"page": 9, "link": 1, "repo": "googleapis/google-api-python-client", "commit": "21af37b"},
{"page": 9, "link": 10, "repo": "microsoft/c9-python-getting-started", "commit": "345c81f"},
{"page": 9, "link": 9, "repo": "jrjohansson/scientific-python-lectures", "commit": "ec4c429"},
{"page": 9, "link": 8, "repo": "grangier/python-goose", "commit": "09023ec"},
{"page": 8, "link": 9, "repo": "EdwinZhang1970/Python", "commit": "be85d00"},
{"page": 9, "link": 6, "repo": "kivy/python-for-android", "commit": "61be5d4"},
{"page": 8, "link": 7, "repo": "facebookarchive/python-instagram", "commit": "da51708"},
{"page": 9, "link": 5, "repo": "bear/python-twitter", "commit": "acd9472"},
{"page": 9, "link": 4, "repo": "arogozhnikov/python3_with_pleasure", "commit": "aae5fa3"},
{"page": 9, "link": 3, "repo": "roytuts/python", "commit": "9897d4c"},
{"page": 9, "link": 2, "repo": "scikit-learn/scikit-learn", "commit": "195f2f4"},
{"page": 10, "link": 10, "repo": "googleapis/google-cloud-python", "commit": "c5781bf"},
{"page": 10, "link": 9, "repo": "Miserlou/Zappa", "commit": "93804a1"},
{"page": 10, "link": 8, "repo": "sammchardy/python-binance", "commit": "2c2b3bf"},
{"page": 10, "link": 7, "repo": "michaelliao/awesome-python-webapp", "commit": "590bea9"},
{"page": 10, "link": 6, "repo": "egrcc/zhihu-python", "commit": "1e24d4d"},
{"page": 10, "link": 5, "repo": "albertlauncher/python", "commit": "bbc0d9d"},
{"page": 10, "link": 4, "repo": "marblexu/PythonPlantsVsZombies", "commit": "afc4ae1"},
{"page": 9, "link": 7, "repo": "jerrywu2013/Python", "commit": "dbb2011"},
{"page": 10, "link": 3, "repo": "ujjwalkarn/DataSciencePython", "commit": "524af79"},
{"page": 10, "link": 2, "repo": "kenwoodjw/python_interview_question", "commit": "a8c3252"},
{"page": 10, "link": 1, "repo": "lawlite19/MachineLearning_Python", "commit": "fc954f6"},
{"page": 11, "link": 1, "repo": "trekhleb/learn-python", "commit": "427de77"},
{"page": 11, "link": 10, "repo": "slackapi/python-slackclient", "commit": "77a125a"},
{"page": 11, "link": 9, "repo": "yasoob/intermediatePython", "commit": "e7bbb9b"},
{"page": 11, "link": 8, "repo": "tweepy/tweepy", "commit": "c292372"},
{"page": 11, "link": 7, "repo": "gitpython-developers/GitPython", "commit": "9b7839e"},
{"page": 11, "link": 5, "repo": "jackzhenguo/python-small-examples", "commit": "ea33101"},
{"page": 11, "link": 4, "repo": "getsentry/raven-python", "commit": "285b257"},
{"page": 11, "link": 3, "repo": "30-seconds/30-seconds-of-python", "commit": "42614dd"},
{"page": 11, "link": 2, "repo": "pythonnet/pythonnet", "commit": "ec424bb"},
{"page": 12, "link": 10, "repo": "codebasics/py", "commit": "050d639"},
{"page": 12, "link": 9, "repo": "joestump/python-oauth2", "commit": "b94f69b"},
{"page": 12, "link": 7, "repo": "pyenv/pyenv", "commit": "ece59ca"},
{"page": 12, "link": 6, "repo": "sixu05202004/pythontutorial3", "commit": "691bc33"},
{"page": 12, "link": 5, "repo": "python-openxml/python-docx", "commit": "da75fcf"},
{"page": 12, "link": 4, "repo": "dibgerge/ml-coursera-python-assignments", "commit": "ec39a68"},
{"page": 12, "link": 3, "repo": "shadowsocksr-backup/shadowsocksr", "commit": "1ee3442"},
{"page": 12, "link": 2, "repo": "omab/python-social-auth", "commit": "81c0a54"},
{"page": 11, "link": 6, "repo": "pluralsight-projects/PythonFlask-JobBoard", "commit": "3f36202"},
{"page": 12, "link": 1, "repo": "vipstone/python", "commit": "99b8082"},
{"page": 13, "link": 1, "repo": "codebasics/py", "commit": "050d639"},
{"page": 13, "link": 10, "repo": "susanli2016/NLP-with-Python", "commit": "30d62f0"},
{"page": 13, "link": 9, "repo": "mongodb/mongo-python-driver", "commit": "84fd04e"},
{"page": 13, "link": 7, "repo": "rlabbe/Kalman-and-Bayesian-Filters-in-Python", "commit": "91f8010"},
{"page": 13, "link": 6, "repo": "pyecharts/pyecharts", "commit": "ca1c783"},
{"page": 13, "link": 5, "repo": "rasbt/python_reference", "commit": "d6ddacb"},
{"page": 13, "link": 4, "repo": "crossbario/autobahn-python", "commit": "372c2dd"},
{"page": 12, "link": 8, "repo": "glix/python", "commit": "715a6e5"},
{"page": 13, "link": 3, "repo": "mne-tools/mne-python", "commit": "126cf98"},
{"page": 13, "link": 2, "repo": "jakevdp/WhirlwindTourOfPython", "commit": "6f1daf7"},
{"page": 14, "link": 1, "repo": "susanli2016/NLP-with-Python", "commit": "30d62f0"},
{"page": 14, "link": 7, "repo": "rasbt/python-machine-learning-book-2nd-edition", "commit": "1b01e73"},
{"page": 14, "link": 6, "repo": "python/pythondotorg", "commit": "daab61a"},
{"page": 14, "link": 5, "repo": "ZiniuLu/Python-100-Days", "commit": "d4d159d"},
{"page": 13, "link": 8, "repo": "heroku/heroku-buildpack-python", "commit": "42507a3"},
{"page": 14, "link": 2, "repo": "googlemaps/google-maps-services-python", "commit": "104ab34"},
{"page": 15, "link": 1, "repo": "dronekit/dronekit-python", "commit": "fe6c623"},
{"page": 15, "link": 10, "repo": "pypa/pip", "commit": "acab2ee"},
{"page": 15, "link": 7, "repo": "andymccurdy/redis-py", "commit": "7e466f7"},
{"page": 15, "link": 6, "repo": "pythonprobr/pythonbirds", "commit": "e0ba8e8"},
{"page": 14, "link": 10, "repo": "Yeah-Kun/python", "commit": "226f9db"},
{"page": 14, "link": 9, "repo": "Novice-Paradigm/Python", "commit": "ba8ca08"},
{"page": 14, "link": 8, "repo": "LightTable/Python", "commit": "9b1c192"},
{"page": 15, "link": 5, "repo": "HaoZhang95/Python24", "commit": "771a3f4"},
{"page": 15, "link": 4, "repo": "Kaggle/docker-python", "commit": "668c0b1"},
{"page": 15, "link": 3, "repo": "pgbovine/OnlinePythonTutor", "commit": "b205b4d"},
{"page": 14, "link": 4, "repo": "AllAlgorithms/python", "commit": "722817f"},
{"page": 14, "link": 3, "repo": "watson-developer-cloud/python-sdk", "commit": "83370b7"},
{"page": 15, "link": 2, "repo": "secdev/scapy", "commit": "cb13a5f"},
{"page": 16, "link": 1, "repo": "Python3WebSpider/Python3WebSpider", "commit": "aa03484"},
{"page": 16, "link": 10, "repo": "mGalarnyk/Python_Tutorials", "commit": "c4f7d41"},
{"page": 16, "link": 9, "repo": "qiwsir/StarterLearningPython", "commit": "f4b974f"},
{"page": 16, "link": 8, "repo": "facert/python-data-structure-cn", "commit": "9917111"},
{"page": 15, "link": 8, "repo": "Santostang/PythonScraping", "commit": "96c2fcf"},
{"page": 15, "link": 9, "repo": "dockerfile/python", "commit": "54da399"},
{"page": 16, "link": 6, "repo": "realpython/python-scripts", "commit": "cb448c2"},
{"page": 16, "link": 4, "repo": "mozillazg/python-pinyin", "commit": "09d12d1"},
{"page": 16, "link": 3, "repo": "WillKoehrsen/Data-Analysis", "commit": "2a19473"},
{"page": 16, "link": 2, "repo": "kkroening/ffmpeg-python", "commit": "4cb7d26"},
{"page": 17, "link": 1, "repo": "liwanlei/jiekou-python3", "commit": "dc0a2f8"},
{"page": 17, "link": 10, "repo": "tirthajyoti/Machine-Learning-with-Python", "commit": "659439a"},
{"page": 17, "link": 8, "repo": "lincolnloop/python-qrcode", "commit": "fa22046"},
{"page": 17, "link": 6, "repo": "prompt-toolkit/python-prompt-toolkit", "commit": "beb9b26"},
{"page": 17, "link": 5, "repo": "MichalDanielDobrzanski/DeepLearningPython35", "commit": "ea229ac"},
{"page": 17, "link": 4, "repo": "eastlakeside/interpy-zh", "commit": "7421296"},
{"page": 17, "link": 3, "repo": "xuanhun/PythonHackingBook1", "commit": "8e80abd"},
{"page": 17, "link": 2, "repo": "twilio/twilio-python", "commit": "5ce7ee7"},
{"page": 16, "link": 7, "repo": "ictar/python-doc", "commit": "f6da137"},
{"page": 16, "link": 5, "repo": "g0t0wasd/python", "commit": "45edac7"},
{"page": 18, "link": 1, "repo": "dloss/python-pentest-tools", "commit": "e8cf781"},
{"page": 18, "link": 10, "repo": "Prodesire/Python-Guide-CN", "commit": "ce12dbe"},
{"page": 18, "link": 9, "repo": "danpaquin/coinbasepro-python", "commit": "19cac25"},
{"page": 18, "link": 8, "repo": "fonnesbeck/statistical-analysis-python-tutorial", "commit": "4a2444f"},
{"page": 18, "link": 7, "repo": "sendgrid/sendgrid-python", "commit": "3415520"},
{"page": 18, "link": 6, "repo": "Ehco1996/Python-crawler", "commit": "e89ef77"},
{"page": 17, "link": 9, "repo": "makelove/OpenCV-Python-Tutorial", "commit": "4107158"},
{"page": 18, "link": 5, "repo": "prometheus/client_python", "commit": "dd93abe"},
{"page": 17, "link": 7, "repo": "361way/python", "commit": "81359ac"},
{"page": 18, "link": 4, "repo": "1qweasdzxc/python", "commit": "11611e0"},
{"page": 18, "link": 2, "repo": "Azure/azure-sdk-for-python", "commit": "f3522cd"},
{"page": 19, "link": 1, "repo": "satwikkansal/wtfpython", "commit": "3ba87fe"},
{"page": 19, "link": 10, "repo": "ctgk/PRML", "commit": "63499ff"},
{"page": 19, "link": 9, "repo": "AllenDowney/ThinkPython2", "commit": "96e0091"},
{"page": 19, "link": 8, "repo": "wzy6642/Machine-Learning-in-Action-Python3", "commit": "3710796"},
{"page": 19, "link": 5, "repo": "mvantellingen/python-zeep", "commit": "0d21568"},
{"page": 19, "link": 4, "repo": "Kill-Console/PythonShootGame", "commit": "1bb9552"},
{"page": 19, "link": 3, "repo": "influxdata/influxdb-python", "commit": "fc0235e"},
{"page": 19, "link": 2, "repo": "0rpc/zerorpc-python", "commit": "3d0a6ee"},
{"page": 19, "link": 7, "repo": "strawlab/python-pcl", "commit": "1d83d2d"},
{"page": 20, "link": 1, "repo": "ctgk/PRML", "commit": "63499ff"},
{"page": 18, "link": 3, "repo": "LeoJr2015/python", "commit": "bb3271b"},
{"page": 20, "link": 10, "repo": "Northxw/Python3_WebSpider", "commit": "9030445"},
{"page": 20, "link": 9, "repo": "JushuangQiao/Python-Offer", "commit": "9eaf533"},
{"page": 20, "link": 8, "repo": "spmallick/learnopencv", "commit": "a71fe61"},
{"page": 20, "link": 6, "repo": "heroku/python-getting-started", "commit": "9a41ac0"},
{"page": 20, "link": 5, "repo": "veox/python3-krakenex", "commit": "742aed5"},
{"page": 20, "link": 4, "repo": "petertodd/python-bitcoinlib", "commit": "78aaaf6"},
{"page": 20, "link": 3, "repo": "ocelma/python-recsys", "commit": "6c6343c"},
{"page": 20, "link": 2, "repo": "ipinfo/python", "commit": "023a15c"},
{"page": 19, "link": 6, "repo": "tomlinNTUB/Python", "commit": "42cba29"},
{"page": 20, "link": 7, "repo": "4rsh/python", "commit": "9fdb602"}
]